MANIFEST.in
README.txt
setup.py
docs/HISTORY.txt
docs/INSTALL.txt
docs/LICENSE.GPL
docs/LICENSE.txt
uwosh/__init__.py
uwosh.simpleemergency.egg-info/PKG-INFO
uwosh.simpleemergency.egg-info/SOURCES.txt
uwosh.simpleemergency.egg-info/dependency_links.txt
uwosh.simpleemergency.egg-info/entry_points.txt
uwosh.simpleemergency.egg-info/namespace_packages.txt
uwosh.simpleemergency.egg-info/not-zip-safe
uwosh.simpleemergency.egg-info/requires.txt
uwosh.simpleemergency.egg-info/top_level.txt
uwosh/simpleemergency/__init__.py
uwosh/simpleemergency/configure.zcml
uwosh/simpleemergency/events.py
uwosh/simpleemergency/interfaces.py
uwosh/simpleemergency/permissions.zcml
uwosh/simpleemergency/setuphandlers.py
uwosh/simpleemergency/subscribers.py
uwosh/simpleemergency/version.txt
uwosh/simpleemergency/browser/__init__.py
uwosh/simpleemergency/browser/configure.zcml
uwosh/simpleemergency/browser/controlpanel.py
uwosh/simpleemergency/browser/emergencystyle.css
uwosh/simpleemergency/browser/simpleemergency.pt
uwosh/simpleemergency/browser/viewlets.py
uwosh/simpleemergency/profiles/default/browserlayer.xml
uwosh/simpleemergency/profiles/default/controlpanel.xml
uwosh/simpleemergency/profiles/default/cssregistry.xml
uwosh/simpleemergency/profiles/default/import_steps.xml
uwosh/simpleemergency/profiles/default/metadata.xml
uwosh/simpleemergency/profiles/default/propertiestool.xml
uwosh/simpleemergency/profiles/default/rolemap.xml
uwosh/simpleemergency/profiles/default/uwosh.simpleemergency_marker.txt
uwosh/simpleemergency/profiles/default/viewlets.xml
uwosh/simpleemergency/profiles/uninstall/cssregistry.xml
uwosh/simpleemergency/profiles/uninstall/viewlets.xml