Metadata-Version: 1.0
Name: uwosh.simpleemergency
Version: 1.0.1
Summary: This product creates a viewlet that can be configured to show emergency noticiations
Home-page: https://141.233.238.172/svn/plone/Projects/uwosh.simpleemergency/
Author: Nathan Van Gheem
Author-email: vangheem@gmail.com
License: GPL
Platform: UNKNOWN
Classifier: Framework :: Plone
Classifier: Programming Language :: Python
Classifier: Topic :: Software Development :: Libraries :: Python Modules
